gtool/LICENSE
gtool/__init__.py
gtool/core/__init__.py
gtool/core/aggregatorregistry/__init__.py
gtool/core/filewalker/__init__.py
gtool/core/namespace/__init__.py
gtool/core/noderegistry/__init__.py
gtool/core/plugin/__init__.py
gtool/core/projecttemplate/.GTOOLVERSION
gtool/core/projecttemplate/gtool.cfg
gtool/core/projecttemplate/aggregates/example.txt
gtool/core/projecttemplate/classes/exampleclass.txt
gtool/core/projecttemplate/data/example1.txt
gtool/core/projecttemplate/data/example2/_.txt
gtool/core/projecttemplate/data/example2/num2.txt
gtool/core/projecttemplate/plugins/dummy.py
gtool/core/types/__init__.py
gtool/core/types/attributes.py
gtool/core/types/core.py
gtool/core/types/matrix.py
gtool/core/types/output.py
gtool/core/types/outputmanagers.py
gtool/core/utils/__init__.py
gtool/core/utils/aggregatorprocessor.py
gtool/core/utils/classprocessor.py
gtool/core/utils/misc.py
gtool/core/utils/scaffold.py
gtool/core/utils/classgen/__init__.py
gtool/core/utils/command/__init__.py
gtool/core/utils/command/listelements.py
gtool/core/utils/command/process.py
gtool/core/utils/config/__init__.py
gtool/core/utils/output/__init__.py
gtool/core/utils/runtime/__init__.py
gtool/plugins/artefacts.py
gtool/plugins/average.py
gtool/plugins/choice.py
gtool/plugins/combine.py
gtool/plugins/csv.py
gtool/plugins/cvssv2.py
gtool/plugins/date.py
gtool/plugins/decisiontree.py
gtool/plugins/directedgraph.py
gtool/plugins/enum.py
gtool/plugins/excel.py
gtool/plugins/filename.py
gtool/plugins/fullpath.py
gtool/plugins/grid.py
gtool/plugins/json.py
gtool/plugins/listing.py
gtool/plugins/math.py
gtool/plugins/nodename.py
gtool/plugins/number.py
gtool/plugins/parent.py
gtool/plugins/path.py
gtool/plugins/real.py
gtool/plugins/ref.py
gtool/plugins/slice.py
gtool/plugins/static.py
gtool/plugins/string.py
gtool/plugins/sum.py
gtool/plugins/url.py
gtool/plugins/xattrib.py
gtool/plugins/yaml.py
gtool-0.1.12.dist-info/DESCRIPTION.rst
gtool-0.1.12.dist-info/METADATA
gtool-0.1.12.dist-info/RECORD
gtool-0.1.12.dist-info/WHEEL
gtool-0.1.12.dist-info/entry_points.txt
gtool-0.1.12.dist-info/metadata.json
gtool-0.1.12.dist-info/top_level.txt
test/__init__.py
