Metadata-Version: 2.0
Name: gtool
Version: 0.1.12
Summary: A framework for building security governance, risk and compliance tools.
Home-page: https://gtoolframework.github.io/
Author: Ben Sapiro
Author-email: https://ca.linkedin.com/in/sapiro
License: GPLv3
Download-URL: https://github.com/gtoolframework/gtool/tarball/0.1.12
Keywords: security risk governance compliance framework
Platform: UNKNOWN
Classifier: Development Status :: 4 - Beta
Classifier: Topic :: Utilities
Classifier: Topic :: Software Development :: Libraries :: Application Frameworks
Classifier: Environment :: Console
Classifier: License :: OSI Approved :: GNU General Public License v3 (GPLv3)
Classifier: Intended Audience :: Information Technology
Classifier: Natural Language :: English
Classifier: Operating System :: OS Independent
Classifier: Programming Language :: Python :: 3.5
Requires-Dist: PyYAML
Requires-Dist: XlsxWriter
Requires-Dist: boltons
Requires-Dist: click
Requires-Dist: configparser
Requires-Dist: cvsslib
Requires-Dist: decorator
Requires-Dist: networkx
Requires-Dist: patricia-trie
Requires-Dist: pluginbase
Requires-Dist: pydot
Requires-Dist: pyparsing
Requires-Dist: simpleeval
Requires-Dist: six
Requires-Dist: validators
